{
  "name": "Component9",
  "declarations": "clock x, y, z;",
  "locations": [
    {
      "id": "L23",
      "nickname": "",
      "invariant": "",
      "type": "INITIAL",
      "urgency": "NORMAL",
      "x": 125.0,
      "y": 250.0,
      "color": "1",
      "nicknameX": 30.0,
      "nicknameY": -10.0,
      "invariantX": 30.0,
      "invariantY": 10.0
    },
    {
      "id": "L24",
      "nickname": "",
      "invariant": "",
      "type": "NORMAL",
      "urgency": "NORMAL",
      "x": 133.60001,
      "y": 417.02,
      "color": "1",
      "nicknameX": 30.0,
      "nicknameY": -10.0,
      "invariantX": 30.0,
      "invariantY": 10.0
    },
    {
      "id": "L25",
      "nickname": "",
      "invariant": "",
      "type": "NORMAL",
      "urgency": "NORMAL",
      "x": 356.66000999999994,
      "y": 246.83999999999997,
      "color": "1",
      "nicknameX": 30.0,
      "nicknameY": -10.0,
      "invariantX": 30.0,
      "invariantY": 10.0
    },
    {
      "id": "L26",
      "nickname": "",
      "invariant": "",
      "type": "NORMAL",
      "urgency": "NORMAL",
      "x": 356.12001,
      "y": 418.09999999999997,
      "color": "1",
      "nicknameX": 30.0,
      "nicknameY": -10.0,
      "invariantX": 30.0,
      "invariantY": 10.0
    }
  ],
  "edges": [
    {
      "id": "E16",
      "group": "",
      "sourceLocation": "L23",
      "targetLocation": "L24",
      "status": "INPUT",
      "select": "",
      "guard": "x\u003c5",
      "update": "",
      "sync": "",
      "isLocked": false,
      "nails": [
        {
          "x": 130.0,
          "y": 300.0,
          "propertyType": "GUARD",
          "propertyX": 10.0,
          "propertyY": 0.0
        },
        {
          "x": 133.6,
          "y": 366.12,
          "propertyType": "SYNCHRONIZATION",
          "propertyX": 10.0,
          "propertyY": 0.0
        }
      ]
    },
    {
      "id": "E17",
      "group": "",
      "sourceLocation": "L23",
      "targetLocation": "L25",
      "status": "INPUT",
      "select": "",
      "guard": "x\u003e5",
      "update": "",
      "sync": "",
      "isLocked": false,
      "nails": [
        {
          "x": 200.0,
          "y": 250.0,
          "propertyType": "GUARD",
          "propertyX": 10.0,
          "propertyY": 0.0
        },
        {
          "x": 280.0,
          "y": 249.99999999999994,
          "propertyType": "SYNCHRONIZATION",
          "propertyX": 10.0,
          "propertyY": 0.0
        }
      ]
    },
    {
      "id": "E18",
      "group": "",
      "sourceLocation": "L25",
      "targetLocation": "L26",
      "status": "INPUT",
      "select": "",
      "guard": "",
      "update": "",
      "sync": "",
      "isLocked": false,
      "nails": [
        {
          "x": 356.3,
          "y": 317.38,
          "propertyType": "SYNCHRONIZATION",
          "propertyX": 10.0,
          "propertyY": 0.0
        }
      ]
    },
    {
      "id": "E19",
      "group": "",
      "sourceLocation": "L24",
      "targetLocation": "L26",
      "status": "INPUT",
      "select": "",
      "guard": "",
      "update": "",
      "sync": "",
      "isLocked": false,
      "nails": [
        {
          "x": 274.86,
          "y": 417.38,
          "propertyType": "SYNCHRONIZATION",
          "propertyX": 10.0,
          "propertyY": 0.0
        }
      ]
    }
  ],
  "description": "",
  "x": 65.0,
  "y": 14.5,
  "width": 450.0,
  "height": 600.0,
  "color": "1",
  "includeInPeriodicCheck": true
}