{
  "name": "Component5",
  "declarations": "clock x, y, z;",
  "locations": [
    {
      "id": "L11",
      "nickname": "",
      "invariant": "x\u003e5",
      "type": "INITIAL",
      "urgency": "NORMAL",
      "x": 85.0,
      "y": 310.0,
      "color": "2",
      "nicknameX": 30.0,
      "nicknameY": -10.0,
      "invariantX": -3.552713678800501E-15,
      "invariantY": 30.0
    },
    {
      "id": "L12",
      "nickname": "",
      "invariant": "x\u003c5",
      "type": "NORMAL",
      "urgency": "NORMAL",
      "x": 330.00001,
      "y": 312.0,
      "color": "2",
      "nicknameX": 30.0,
      "nicknameY": -10.0,
      "invariantX": -3.552713678800501E-15,
      "invariantY": 30.0
    }
  ],
  "edges": [
    {
      "id": "E8",
      "group": "",
      "sourceLocation": "L11",
      "targetLocation": "L12",
      "status": "INPUT",
      "select": "",
      "guard": "",
      "update": "x\u003d0",
      "sync": "",
      "isLocked": false,
      "nails": [
        {
          "x": 160.0,
          "y": 310.0,
          "propertyType": "SYNCHRONIZATION",
          "propertyX": 10.0,
          "propertyY": 0.0
        },
        {
          "x": 240.0,
          "y": 310.0,
          "propertyType": "UPDATE",
          "propertyX": 10.0,
          "propertyY": 0.0
        }
      ]
    }
  ],
  "description": "",
  "x": 65.0,
  "y": 14.5,
  "width": 450.0,
  "height": 600.0,
  "color": "2",
  "includeInPeriodicCheck": true
}